ethernetip/__init__.py
ethernetip/ethernetip.py
ethernetip-1.1.2.dist-info/LICENSE
ethernetip-1.1.2.dist-info/METADATA
ethernetip-1.1.2.dist-info/WHEEL
ethernetip-1.1.2.dist-info/top_level.txt
ethernetip-1.1.2.dist-info/RECORD
